regression_enrichment_surface/__init__.py
regression_enrichment_surface/regression_enrichment_surface.py
regression_enrichment_surface-0.3.0.dist-info/AUTHORS.rst
regression_enrichment_surface-0.3.0.dist-info/LICENSE
regression_enrichment_surface-0.3.0.dist-info/METADATA
regression_enrichment_surface-0.3.0.dist-info/WHEEL
regression_enrichment_surface-0.3.0.dist-info/top_level.txt
regression_enrichment_surface-0.3.0.dist-info/RECORD
