Metadata-Version: 2.1
Name: regression-enrichment-surface
Version: 0.3.0
Summary: Code for producing regression enrichment analysis
Home-page: https://github.com/aclyde11/regression_enrichment_surface
Author: Austin Clyde
Author-email: aclyde@uchicago.edu
License: MIT license
Keywords: regression_enrichment_surface
Platform: UNKNOWN
Classifier: Development Status :: 2 - Pre-Alpha
Classifier: Intended Audience :: Developers
Classifier: License :: OSI Approved :: MIT License
Classifier: Natural Language :: English
Classifier: Programming Language :: Python :: 3
Classifier: Programming Language :: Python :: 3.5
Classifier: Programming Language :: Python :: 3.6
Classifier: Programming Language :: Python :: 3.7
Classifier: Programming Language :: Python :: 3.8
Requires-Python: >=3.5
